django_telethon_multisession/__init__.py
django_telethon_multisession/admin.py
django_telethon_multisession/apps.py
django_telethon_multisession/models.py
django_telethon_multisession/sessions.py
django_telethon_multisession/migrations/0001_initial.py
django_telethon_multisession/migrations/__init__.py
django_telethon_multisession-0.5.dist-info/LICENSE
django_telethon_multisession-0.5.dist-info/METADATA
django_telethon_multisession-0.5.dist-info/WHEEL
django_telethon_multisession-0.5.dist-info/top_level.txt
django_telethon_multisession-0.5.dist-info/RECORD
