Metadata-Version: 2.1
Name: django-telethon-multisession
Version: 0.5
Summary: Telethon Session 
Home-page: https://github.com/sinarezaei/django-telethon-multisession
Author: Sina Rezaei
Author-email: sinarezaei1991@gmail.com
License: MIT
Platform: UNKNOWN
Classifier: Programming Language :: Python :: 3
Classifier: License :: OSI Approved :: MIT License
Classifier: Operating System :: OS Independent
